LICENSE
MANIFEST.in
README
gendoc.py
setup.py
docs/httpclient.m.html
docs/index.html
docs/sms.m.html
docs/util.m.html
docs/voice.m.html
qcloudsms_py/__init__.py
qcloudsms_py/httpclient.py
qcloudsms_py/sms.py
qcloudsms_py/util.py
qcloudsms_py/voice.py
qcloudsms_py.egg-info/PKG-INFO
qcloudsms_py.egg-info/SOURCES.txt
qcloudsms_py.egg-info/dependency_links.txt
qcloudsms_py.egg-info/top_level.txt